apscale_renamer/__init__.py
apscale_renamer/__main__.py
apscale_renamer-0.1.dist-info/LICENSE
apscale_renamer-0.1.dist-info/METADATA
apscale_renamer-0.1.dist-info/WHEEL
apscale_renamer-0.1.dist-info/entry_points.txt
apscale_renamer-0.1.dist-info/top_level.txt
apscale_renamer-0.1.dist-info/RECORD
